ampy/__init__.py
ampy/cli.py
ampy/files.py
ampy/pyboard.py
encukou_ampy-1.0.7.1.dist-info/LICENSE
encukou_ampy-1.0.7.1.dist-info/METADATA
encukou_ampy-1.0.7.1.dist-info/WHEEL
encukou_ampy-1.0.7.1.dist-info/entry_points.txt
encukou_ampy-1.0.7.1.dist-info/top_level.txt
encukou_ampy-1.0.7.1.dist-info/RECORD
