Metadata-Version: 2.1
Name: encukou-ampy
Version: 1.0.7.1
Summary: ampy (Adafruit MicroPython tool) is a command line tool to interact with a CircuitPython or MicroPython board over a serial connection.
Home-page: https://github.com/encukou/ampy
Author: Adafruit Industries
Author-email: circuitpython@adafruit.com
Maintainer: Petr Viktorin
Maintainer-email: encukou@gmail.com.com
License: MIT
Keywords: ampy hardware micropython
Platform: UNKNOWN
Classifier: Development Status :: 4 - Beta
Classifier: Intended Audience :: Developers
Classifier: License :: OSI Approved :: MIT License
Classifier: Programming Language :: Python :: 2
Classifier: Programming Language :: Python :: 2.6
Classifier: Programming Language :: Python :: 2.7
Classifier: Programming Language :: Python :: 3
Classifier: Programming Language :: Python :: 3.3
Classifier: Programming Language :: Python :: 3.4
Classifier: Programming Language :: Python :: 3.5
Requires-Dist: click
Requires-Dist: pyserial
Requires-Dist: python-dotenv
